color_log/__init__.py
color_log/clog.py
py_color_log-1.0.4.dist-info/LICENSE.txt
py_color_log-1.0.4.dist-info/METADATA
py_color_log-1.0.4.dist-info/WHEEL
py_color_log-1.0.4.dist-info/top_level.txt
py_color_log-1.0.4.dist-info/RECORD
