Metadata-Version: 2.1
Name: py-color-log
Version: 1.0.4
Summary: python color log
Home-page: https://github.com/lyy289065406/py-color-log
Author: EXP
Author-email: 289065406@qq.com
Project-URL: Bug Reports, https://github.com/lyy289065406/py-color-log/issues
Project-URL: Funding, https://github.com/lyy289065406/py-color-log/blob/master/imgs/donate-alipay.png
Project-URL: Say Thanks!, https://github.com/lyy289065406/py-color-log/blob/master/imgs/donate-wechat.png
Project-URL: Source, https://github.com/lyy289065406/py-color-log/
Keywords: color,log
Classifier: Development Status :: 3 - Alpha
Classifier: Intended Audience :: Developers
Classifier: Topic :: Software Development :: Build Tools
Classifier: License :: OSI Approved :: MIT License
Classifier: Programming Language :: Python :: 3
Classifier: Programming Language :: Python :: 3.5
Classifier: Programming Language :: Python :: 3.6
Classifier: Programming Language :: Python :: 3.7
Classifier: Programming Language :: Python :: 3.8
Classifier: Programming Language :: Python :: 3 :: Only
Requires-Python: >=3.5, <4
License-File: LICENSE.txt
Requires-Dist: colorlog (>=6.6.0)
Provides-Extra: dev
Requires-Dist: check-manifest ; extra == 'dev'
Provides-Extra: test
Requires-Dist: coverage ; extra == 'test'
